sideload_caddy_2_bin_6633ecaead19ca34f863955b/__init__.py
sideload_caddy_2_bin_6633ecaead19ca34f863955b/caddy_2.7.6_windows_arm64.zip.sig
sideload_caddy_2_bin_6633ecaead19ca34f863955b-1.0.0.dist-info/METADATA
sideload_caddy_2_bin_6633ecaead19ca34f863955b-1.0.0.dist-info/WHEEL
sideload_caddy_2_bin_6633ecaead19ca34f863955b-1.0.0.dist-info/top_level.txt
sideload_caddy_2_bin_6633ecaead19ca34f863955b-1.0.0.dist-info/RECORD
